
  {
    "id": "variant-001",
    "name": "Classic Starter",
    "ownerId": "system",
    "namedVariant": "CLASSIC",
    "farmTemplate": {
      "id": "farm-1",
      "name": "Starter Farm",
      "sizeX": 20,
      "sizeY": 15,
      "blockSize": 1,
      "plots": [ { "x": 1, "y": 1, "sizeX": 1, "sizeY": 1, "asset": { "id": "asset-ground-1" }, "cropId": "parsnip", "plantedAt": "2025-01-01T00:00:00Z", "growthStage": 0, "isWatered": false } ],
      "decorations": [ { "x": 0, "y": 0, "sizeX": 1, "sizeY": 1, "asset": { "id": "asset-deco-1" } } ]
    },
    "barnTemplate": {
      "id": "barn-1",
      "name": "Starter Barn",
      "sizeX": 10,
      "sizeY": 6,
      "blockSize": 1,
      "pens": [ { "x": 1, "y": 1, "sizeX": 2, "sizeY": 2, "asset": { "id": "asset-pen-1" }, "animalIds": ["cow-1"], "capacity": 2 } ],
      "storageUnits": [ { "x": 2, "y": 2, "sizeX": 1, "sizeY": 1, "asset": { "id": "asset-storage-1" }, "storageId": "s1", "capacity": 10 } ]
    },
    "minesTemplate": {
      "id": "mines-1",
      "name": "Starter Mines",
      "currentLevel": 1,
      "maxLevel": 5,
      "levels": [ {
        "level": 1,
        "sizeX": 8,
        "sizeY": 8,
        "blockSize": 1,
        "tiles": [ { "x": 0, "y": 0, "sizeX": 1, "sizeY": 1, "asset": { "id": "asset-stone-1" }, "resourceId": "stone", "resourceQuantity": 3, "discovered": true, "timeTaken": 5000 } ],
        "resourceIds": ["stone"],
        "difficulty": 1
      } ]
    },
    "fishingAreaTemplate": {
      "id": "fish-1",
      "name": "Starter Lake",
      "sizeX": 12,
      "sizeY": 7,
      "blockSize": 1,
      "spots": [ { "x": 3, "y": 2, "sizeX": 1, "sizeY": 1, "asset": { "id": "asset-water-1" }, "quality": 2, "specificFishIds": ["anchovy"] } ],
      "availableFishIds": ["anchovy", "sardine"]
    }
  }
